ragorez/common/__init__.py
ragorez/common/text_transformations.py
ragorez_common-0.1.0.dist-info/METADATA
ragorez_common-0.1.0.dist-info/WHEEL
ragorez_common-0.1.0.dist-info/top_level.txt
ragorez_common-0.1.0.dist-info/RECORD
